Metadata-Version: 2.1
Name: aws-cdk.aws-apigatewayv2-authorizers-alpha
Version: 2.114.1a0
Summary: This module is deprecated. All constructs are now available under aws-cdk-lib/aws-apigatewayv2-authorizers
Home-page: https://github.com/aws/aws-cdk
Author: Amazon Web Services
License: Apache-2.0
Project-URL: Source, https://github.com/aws/aws-cdk.git
Classifier: Intended Audience :: Developers
Classifier: Operating System :: OS Independent
Classifier: Programming Language :: JavaScript
Classifier: Programming Language :: Python :: 3 :: Only
Classifier: Programming Language :: Python :: 3.8
Classifier: Programming Language :: Python :: 3.9
Classifier: Programming Language :: Python :: 3.10
Classifier: Programming Language :: Python :: 3.11
Classifier: Typing :: Typed
Classifier: Development Status :: 7 - Inactive
Classifier: License :: OSI Approved
Classifier: Framework :: AWS CDK
Classifier: Framework :: AWS CDK :: 2
Requires-Python: ~=3.8
License-File: LICENSE
License-File: NOTICE
Requires-Dist: aws-cdk-lib <3.0.0,>=2.114.1
Requires-Dist: aws-cdk.aws-apigatewayv2-alpha ==2.114.1.a0
Requires-Dist: constructs <11.0.0,>=10.0.0
Requires-Dist: jsii <2.0.0,>=1.92.0
Requires-Dist: publication >=0.0.3
Requires-Dist: typeguard ~=2.13.3
